glx/__init__.py
glx/gl_importer.py
glx/tools.py
glx/wrappers.py
glx/font/__init__.py
glx/font/atlas.py
glx/font/code_lookup.py
glx/font/display_list.py
glx/font/font.py
glx/glsl_shaders/basic.frag
glx/glsl_shaders/basic.vert
glx/glsl_shaders/text.frag
glx/glsl_shaders/text.geom
glx/glsl_shaders/text.vert
glx/shader_program/__init__.py
glx/shader_program/attribute.py
glx/shader_program/bound_attribute.py
glx/shader_program/buffer_description.py
glx/shader_program/shader.py
glx/shader_program/shader_program.py
glx/shader_program/uniform_description.py
glx/shader_program/vertex_array.py
glx/shader_programs/__init__.py
glx/shader_programs/basic.py
glx/transformations/__init__.py
glx/transformations/test_transformations.py
glx/transformations/transformations.py
glx/viewport/__init__.py
glx/viewport/bounded_ortho_view.py
glx/viewport/ortho_projection.py
glx/viewport/ortho_view.py
glx/viewport/viewport.py
glx/viewport/test/__init__.py
glx/viewport/test/test_conversions.py
glx-0.6.dist-info/LICENSE
glx-0.6.dist-info/METADATA
glx-0.6.dist-info/WHEEL
glx-0.6.dist-info/top_level.txt
glx-0.6.dist-info/RECORD
